[
  {
    "id": 1859,
    "type": "Cover Page",
    "title": "Cover Page",
    "authors": [],
    "abstract": "",
    "abstractHtml": "",
    "previewText": "",
    "keywords": [],
    "doi": "",
    "received": "",
    "accepted": "",
    "published": "1986-01-01",
    "volume": 3,
    "issue": "3",
    "pages": "",
    "views": 0,
    "downloads": 0,
    "citations": 0,
    "featured": false,
    "imageCorner": false,
    "hasFullText": false,
    "sourceIssueId": "1105",
    "sourceArticleId": "1859",
    "sourceAbstractUrl": "",
    "sourceTextUrl": "",
    "sourcePdfUrl": "https://balkanmedicaljournal.org/pdf.php?&id=1859",
    "localPdfUrl": "js/data/pdfs/1859.pdf",
    "pdfUrl": "js/data/pdfs/1859.pdf"
  },
  {
    "id": 542,
    "type": "Original Article",
    "title": "The Role of Mast Cell Depletion On the Acute Toxicity of Morphia In Mice",
    "authors": [
      {
        "name": "İ. Dökmeci",
        "affiliation": "Trakya Üniversitesi Tıp Fakültesi Farmakoloji ve Toksikoloji Anabilim Dalı Öğretim Üyesi",
        "orcid": ""
      },
      {
        "name": "A. Akcasu [[2]] <",
        "affiliation": "",
        "orcid": ""
      }
    ],
    "abstract": "",
    "abstractHtml": "",
    "previewText": "",
    "keywords": [],
    "doi": "",
    "received": "",
    "accepted": "",
    "published": "1986-01-01",
    "volume": 3,
    "issue": "3",
    "pages": "3-10",
    "views": 5690,
    "downloads": 1682,
    "citations": 0,
    "featured": false,
    "imageCorner": false,
    "hasFullText": false,
    "sourceIssueId": "1105",
    "sourceArticleId": "542",
    "sourceAbstractUrl": "https://balkanmedicaljournal.org/abstract.php?id=542",
    "sourceTextUrl": "https://balkanmedicaljournal.org/text.php?lang=en&id=542",
    "sourcePdfUrl": "https://balkanmedicaljournal.org/pdf.php?&id=542",
    "localPdfUrl": "js/data/pdfs/542.pdf",
    "pdfUrl": "js/data/pdfs/542.pdf"
  },
  {
    "id": 543,
    "type": "Original Article",
    "title": "Eritrositlerde Glükoz Utilizasyonuna Ultrason",
    "authors": [
      {
        "name": "Ö. Yiğitbaşı",
        "affiliation": "Trakya Üniversitesi Tıp Fakültesi, Nükleer Tıp Anabilim Dalı. Edirne",
        "orcid": ""
      },
      {
        "name": "H. Tunalı",
        "affiliation": "İ Ü. Cerrahpaşa Tıp Fakültesi, Fizyoloji Anabilim Dalı. İstanbul",
        "orcid": ""
      },
      {
        "name": "H. Sarı",
        "affiliation": "İ Ü. Cerrahpaşa Tıp Fakültesi, Fizik Tedavi Anabilim Dalı. İstanbul",
        "orcid": ""
      },
      {
        "name": "D. Önsel",
        "affiliation": "İ Ü. Cerrahpaşa Tıp Fakültesi, Fizik Tedavi Anabilim Dalı. İstanbul",
        "orcid": ""
      }
    ],
    "abstract": "",
    "abstractHtml": "",
    "previewText": "",
    "keywords": [],
    "doi": "",
    "received": "",
    "accepted": "",
    "published": "1986-01-01",
    "volume": 3,
    "issue": "3",
    "pages": "11-15",
    "views": 5611,
    "downloads": 1597,
    "citations": 0,
    "featured": false,
    "imageCorner": false,
    "hasFullText": false,
    "sourceIssueId": "1105",
    "sourceArticleId": "543",
    "sourceAbstractUrl": "https://balkanmedicaljournal.org/abstract.php?id=543",
    "sourceTextUrl": "https://balkanmedicaljournal.org/text.php?lang=en&id=543",
    "sourcePdfUrl": "https://balkanmedicaljournal.org/pdf.php?&id=543",
    "localPdfUrl": "js/data/pdfs/543.pdf",
    "pdfUrl": "js/data/pdfs/543.pdf"
  },
  {
    "id": 545,
    "type": "Original Article",
    "title": "N. Medianus",
    "authors": [
      {
        "name": "M. Yıldırım",
        "affiliation": "Trakya Üniversitesi Tıp Fakültesi Anatomi Bilim Dalı Öğretim Üyesi (Yard. Doç. Dr.) Edirne",
        "orcid": ""
      }
    ],
    "abstract": "",
    "abstractHtml": "",
    "previewText": "",
    "keywords": [],
    "doi": "",
    "received": "",
    "accepted": "",
    "published": "1986-01-01",
    "volume": 3,
    "issue": "3",
    "pages": "16-20",
    "views": 5770,
    "downloads": 1641,
    "citations": 0,
    "featured": false,
    "imageCorner": false,
    "hasFullText": false,
    "sourceIssueId": "1105",
    "sourceArticleId": "545",
    "sourceAbstractUrl": "https://balkanmedicaljournal.org/abstract.php?id=545",
    "sourceTextUrl": "https://balkanmedicaljournal.org/text.php?lang=en&id=545",
    "sourcePdfUrl": "https://balkanmedicaljournal.org/pdf.php?&id=545",
    "localPdfUrl": "js/data/pdfs/545.pdf",
    "pdfUrl": "js/data/pdfs/545.pdf"
  },
  {
    "id": 546,
    "type": "Original Article",
    "title": "Trakya Üniversitesi Tıp Fakültesi Troid Polikliniği Materyalinin Troid Nodülleri Yönünden İncelenmesi *",
    "authors": [
      {
        "name": "Ş. Berkarda",
        "affiliation": "Trakya Üniversitesi Tıp Fakültesi Nükleer Tıp Ana Bilim Dalı Öğretim Üyesi (Yard. Doç. Dr.) Edirne",
        "orcid": ""
      },
      {
        "name": "S. Okay",
        "affiliation": "Trakya Üniversitesi Tıp Fakültesi Nükleer Tıp Araştırma Görevlisi Edirne",
        "orcid": ""
      }
    ],
    "abstract": "",
    "abstractHtml": "",
    "previewText": "",
    "keywords": [],
    "doi": "",
    "received": "",
    "accepted": "",
    "published": "1986-01-01",
    "volume": 3,
    "issue": "3",
    "pages": "41-44",
    "views": 5880,
    "downloads": 1593,
    "citations": 0,
    "featured": false,
    "imageCorner": false,
    "hasFullText": false,
    "sourceIssueId": "1105",
    "sourceArticleId": "546",
    "sourceAbstractUrl": "https://balkanmedicaljournal.org/abstract.php?id=546",
    "sourceTextUrl": "https://balkanmedicaljournal.org/text.php?lang=en&id=546",
    "sourcePdfUrl": "https://balkanmedicaljournal.org/pdf.php?&id=546",
    "localPdfUrl": "js/data/pdfs/546.pdf",
    "pdfUrl": "js/data/pdfs/546.pdf"
  },
  {
    "id": 547,
    "type": "Original Article",
    "title": "Yeni Doğan Sepsislerinin Erken Tanısında NBT ve SNBT Yöntemlerinin Önemi",
    "authors": [
      {
        "name": "Z. Medeni (ABBAN)",
        "affiliation": "Trakya Üniversitesi Tıp Fakültesi Çocuk Sağlığı ve Hastalıkları Ana Bilim Dalı Öğrt. Üyesi (Doç. Dr.) Edirne",
        "orcid": ""
      },
      {
        "name": "I. Yalçın",
        "affiliation": "İstanbul Tıp Fakültesi Çocuk Sağlığı ve Hastalıkları Ana Bilim Dalı Klinik İmmunoloji Allerjive İnfeksiyon Hastalıkları Bilim Dalı Öğretim Üyesi (Doç. Dr.) İstanbul",
        "orcid": ""
      },
      {
        "name": "Ü. Öneş",
        "affiliation": "İstanbul Tıp Fakültesi Çocuk Sağlığı ve Hastalıkları Ana Bilim Dalı Klinik İmmunoloji Allerjive İnfeksiyon Hastalıkları Bilim Dalı Öğretim Üyesi (Prof. Dr.) İstanbul",
        "orcid": ""
      }
    ],
    "abstract": "",
    "abstractHtml": "",
    "previewText": "",
    "keywords": [],
    "doi": "",
    "received": "",
    "accepted": "",
    "published": "1986-01-01",
    "volume": 3,
    "issue": "3",
    "pages": "50-59",
    "views": 5863,
    "downloads": 1625,
    "citations": 0,
    "featured": false,
    "imageCorner": false,
    "hasFullText": false,
    "sourceIssueId": "1105",
    "sourceArticleId": "547",
    "sourceAbstractUrl": "https://balkanmedicaljournal.org/abstract.php?id=547",
    "sourceTextUrl": "https://balkanmedicaljournal.org/text.php?lang=en&id=547",
    "sourcePdfUrl": "https://balkanmedicaljournal.org/pdf.php?&id=547",
    "localPdfUrl": "js/data/pdfs/547.pdf",
    "pdfUrl": "js/data/pdfs/547.pdf"
  },
  {
    "id": 548,
    "type": "Original Article",
    "title": "Lomber Spinal Kanal Darlıkları *",
    "authors": [
      {
        "name": "S. Çobanoğlu",
        "affiliation": "Trakya Üniversitesi Tıp Fakültesi Nöroşirorji Anabilim Dalı Öğretim Üyesi (Yard. Doç. Dr.) Edirne",
        "orcid": ""
      },
      {
        "name": "N. Demircan",
        "affiliation": "GATA-Hayardarpaşa Askeri Hastanesi, Nöroşirürji Kliniği (Yard. Doç.)- İst.",
        "orcid": ""
      },
      {
        "name": "B. Uçar",
        "affiliation": "Devlet Hastanesi Nöroşirürji Kliniği (Uzman Dr.) - Edirne",
        "orcid": ""
      },
      {
        "name": "C. Kuday",
        "affiliation": "Cerrahpaşa Tıp Fakültesi Nöroşürji Anabilim Dalı Öğretim Üyesi (Doç. Dr.) - İst.",
        "orcid": ""
      }
    ],
    "abstract": "",
    "abstractHtml": "",
    "previewText": "",
    "keywords": [],
    "doi": "",
    "received": "",
    "accepted": "",
    "published": "1986-01-01",
    "volume": 3,
    "issue": "3",
    "pages": "60-75",
    "views": 5640,
    "downloads": 1637,
    "citations": 0,
    "featured": false,
    "imageCorner": false,
    "hasFullText": false,
    "sourceIssueId": "1105",
    "sourceArticleId": "548",
    "sourceAbstractUrl": "https://balkanmedicaljournal.org/abstract.php?id=548",
    "sourceTextUrl": "https://balkanmedicaljournal.org/text.php?lang=en&id=548",
    "sourcePdfUrl": "https://balkanmedicaljournal.org/pdf.php?&id=548",
    "localPdfUrl": "js/data/pdfs/548.pdf",
    "pdfUrl": "js/data/pdfs/548.pdf"
  },
  {
    "id": 549,
    "type": "Original Article",
    "title": "Akut İnferior Miyokard İnfarktüsünde Simetidin",
    "authors": [
      {
        "name": "Tuğrul A.",
        "affiliation": "Trakya Üniversitesi Tıp Fakültesi İç Hastalıkları Anabilim Dalı",
        "orcid": ""
      },
      {
        "name": "Özbay G.",
        "affiliation": "Trakya Üniversitesi Tıp Fakültesi İç Hast. Anabilim Dalı Öğrt. Üyesi EDİRNE",
        "orcid": ""
      },
      {
        "name": "Yücel Y.",
        "affiliation": "Trakya Üniversitesi Fen Fak. Öğretim Üyesi - Edirne",
        "orcid": ""
      }
    ],
    "abstract": "",
    "abstractHtml": "",
    "previewText": "",
    "keywords": [],
    "doi": "",
    "received": "",
    "accepted": "",
    "published": "1986-01-01",
    "volume": 3,
    "issue": "3",
    "pages": "76-86",
    "views": 5732,
    "downloads": 1690,
    "citations": 0,
    "featured": false,
    "imageCorner": false,
    "hasFullText": false,
    "sourceIssueId": "1105",
    "sourceArticleId": "549",
    "sourceAbstractUrl": "https://balkanmedicaljournal.org/abstract.php?id=549",
    "sourceTextUrl": "https://balkanmedicaljournal.org/text.php?lang=en&id=549",
    "sourcePdfUrl": "https://balkanmedicaljournal.org/pdf.php?&id=549",
    "localPdfUrl": "js/data/pdfs/549.pdf",
    "pdfUrl": "js/data/pdfs/549.pdf"
  },
  {
    "id": 550,
    "type": "Original Article",
    "title": "Akromioklavikuler Dislokasyonların Tedavisi",
    "authors": [
      {
        "name": "O. U. Çalpur",
        "affiliation": "Trakya Üniversitesi Tıp Fakültesi Ortopedi ve Travmatoloji Anabilim Dalı Öğretim Üyesi (Yard. Doç. Dr.) Edirne",
        "orcid": ""
      }
    ],
    "abstract": "",
    "abstractHtml": "",
    "previewText": "",
    "keywords": [],
    "doi": "",
    "received": "",
    "accepted": "",
    "published": "1986-01-01",
    "volume": 3,
    "issue": "3",
    "pages": "87-94",
    "views": 5856,
    "downloads": 1618,
    "citations": 0,
    "featured": false,
    "imageCorner": false,
    "hasFullText": false,
    "sourceIssueId": "1105",
    "sourceArticleId": "550",
    "sourceAbstractUrl": "https://balkanmedicaljournal.org/abstract.php?id=550",
    "sourceTextUrl": "https://balkanmedicaljournal.org/text.php?lang=en&id=550",
    "sourcePdfUrl": "https://balkanmedicaljournal.org/pdf.php?&id=550",
    "localPdfUrl": "js/data/pdfs/550.pdf",
    "pdfUrl": "js/data/pdfs/550.pdf"
  },
  {
    "id": 551,
    "type": "Original Article",
    "title": "Rhintis Medicamentosa ve Sistematik Etkili Dekonjestanlarla Tedavisi",
    "authors": [
      {
        "name": "İ. Sarıkahya",
        "affiliation": "Trakya Üniversitesi Tıp Fakültesi KBB Anabilim Dalı Öğretim Başkanı (Prof. Dr.) Edirne",
        "orcid": ""
      },
      {
        "name": "A. Karasağlihoğlu [[2]] <",
        "affiliation": "",
        "orcid": ""
      }
    ],
    "abstract": "",
    "abstractHtml": "",
    "previewText": "",
    "keywords": [],
    "doi": "",
    "received": "",
    "accepted": "",
    "published": "1986-01-01",
    "volume": 3,
    "issue": "3",
    "pages": "95-103",
    "views": 5383,
    "downloads": 1709,
    "citations": 0,
    "featured": false,
    "imageCorner": false,
    "hasFullText": false,
    "sourceIssueId": "1105",
    "sourceArticleId": "551",
    "sourceAbstractUrl": "https://balkanmedicaljournal.org/abstract.php?id=551",
    "sourceTextUrl": "https://balkanmedicaljournal.org/text.php?lang=en&id=551",
    "sourcePdfUrl": "https://balkanmedicaljournal.org/pdf.php?&id=551",
    "localPdfUrl": "js/data/pdfs/551.pdf",
    "pdfUrl": "js/data/pdfs/551.pdf"
  },
  {
    "id": 552,
    "type": "Original Article",
    "title": "İsometrik El Sıkma ve Soğuk Uyarı Testlerinin Çift Master Efor Testi İle Karşılaştırılması ve Koroner Arter Hastalıklarına Tanısına Katkısı",
    "authors": [
      {
        "name": "H. Sur",
        "affiliation": "Trakya Üniversitesi Tıp Fakültesi İç Hastalıkları Anabilim Dalı Öğretim Üyesi (Prof. Dr.) Edirne",
        "orcid": ""
      },
      {
        "name": "G. Özbay",
        "affiliation": "Trakya Üniversitesi Tıp Fakültesi İç Hastalıkları Anabilim Dalı - Edirne",
        "orcid": ""
      }
    ],
    "abstract": "",
    "abstractHtml": "",
    "previewText": "",
    "keywords": [],
    "doi": "",
    "received": "",
    "accepted": "",
    "published": "1986-01-01",
    "volume": 3,
    "issue": "3",
    "pages": "104-112",
    "views": 5525,
    "downloads": 1587,
    "citations": 0,
    "featured": false,
    "imageCorner": false,
    "hasFullText": false,
    "sourceIssueId": "1105",
    "sourceArticleId": "552",
    "sourceAbstractUrl": "https://balkanmedicaljournal.org/abstract.php?id=552",
    "sourceTextUrl": "https://balkanmedicaljournal.org/text.php?lang=en&id=552",
    "sourcePdfUrl": "https://balkanmedicaljournal.org/pdf.php?&id=552",
    "localPdfUrl": "js/data/pdfs/552.pdf",
    "pdfUrl": "js/data/pdfs/552.pdf"
  },
  {
    "id": 553,
    "type": "Original Article",
    "title": "Siliyer Aktivitenin Kontrolünde Kolinerjik Mekainzma",
    "authors": [
      {
        "name": "K. Kaymak",
        "affiliation": "Trakya Üniversitesi Tıp Fakültesi Fizyoloji Anabilim Dalı Öğretim Üyesi (Yard. Doç. Dr.) Edirne",
        "orcid": ""
      }
    ],
    "abstract": "",
    "abstractHtml": "",
    "previewText": "",
    "keywords": [],
    "doi": "",
    "received": "",
    "accepted": "",
    "published": "1986-01-01",
    "volume": 3,
    "issue": "3",
    "pages": "121-128",
    "views": 5239,
    "downloads": 1646,
    "citations": 0,
    "featured": false,
    "imageCorner": false,
    "hasFullText": false,
    "sourceIssueId": "1105",
    "sourceArticleId": "553",
    "sourceAbstractUrl": "https://balkanmedicaljournal.org/abstract.php?id=553",
    "sourceTextUrl": "https://balkanmedicaljournal.org/text.php?lang=en&id=553",
    "sourcePdfUrl": "https://balkanmedicaljournal.org/pdf.php?&id=553",
    "localPdfUrl": "js/data/pdfs/553.pdf",
    "pdfUrl": "js/data/pdfs/553.pdf"
  },
  {
    "id": 554,
    "type": "Original Article",
    "title": "İSA",
    "authors": [
      {
        "name": "İ. Bezcioğlu",
        "affiliation": "Trakya Üniversitesi Tıp Fakültesi İç Hastalıkları Anabilim Dalı - Edirne",
        "orcid": ""
      },
      {
        "name": "G. Özbay",
        "affiliation": "Trakya Üniversitesi Tıp Fakültesi İç Hastalıkları Anabilim Dalı - Edirne",
        "orcid": ""
      },
      {
        "name": "Y. Yücel [[2]] <",
        "affiliation": "",
        "orcid": ""
      }
    ],
    "abstract": "",
    "abstractHtml": "",
    "previewText": "",
    "keywords": [],
    "doi": "",
    "received": "",
    "accepted": "",
    "published": "1986-01-01",
    "volume": 3,
    "issue": "3",
    "pages": "129-147",
    "views": 5503,
    "downloads": 1591,
    "citations": 0,
    "featured": false,
    "imageCorner": false,
    "hasFullText": false,
    "sourceIssueId": "1105",
    "sourceArticleId": "554",
    "sourceAbstractUrl": "https://balkanmedicaljournal.org/abstract.php?id=554",
    "sourceTextUrl": "https://balkanmedicaljournal.org/text.php?lang=en&id=554",
    "sourcePdfUrl": "https://balkanmedicaljournal.org/pdf.php?&id=554",
    "localPdfUrl": "js/data/pdfs/554.pdf",
    "pdfUrl": "js/data/pdfs/554.pdf"
  },
  {
    "id": 555,
    "type": "Original Article",
    "title": "1983-1987 Yılları Trakya Üniversitesi Tıp Fakültesi Troid Polikliniği Materyalimizin Değerlendirilmesi",
    "authors": [
      {
        "name": "Ş. Berkarda",
        "affiliation": "Trakya Üniversitesi Tıp Fakültesi Nükleer Tıp Ana Bilim Dalı Öğretim Üyesi (Yard. Doç. Dr.) Edirne",
        "orcid": ""
      },
      {
        "name": "Ö. Yiğitbaşı",
        "affiliation": "Trakya Üniversitesi Tıp Fakültesi, Nükleer Tıp Anabilim Dalı Öğretim Üyesi (Doç. Dr.) Edirne",
        "orcid": ""
      },
      {
        "name": "S. Okay",
        "affiliation": "Trakya Üniversitesi Tıp Fakültesi Nükleer Tıp Ana Bilim Dalı Edirne",
        "orcid": ""
      }
    ],
    "abstract": "",
    "abstractHtml": "",
    "previewText": "",
    "keywords": [],
    "doi": "",
    "received": "",
    "accepted": "",
    "published": "1986-01-01",
    "volume": 3,
    "issue": "3",
    "pages": "148-152",
    "views": 5640,
    "downloads": 1609,
    "citations": 0,
    "featured": false,
    "imageCorner": false,
    "hasFullText": false,
    "sourceIssueId": "1105",
    "sourceArticleId": "555",
    "sourceAbstractUrl": "https://balkanmedicaljournal.org/abstract.php?id=555",
    "sourceTextUrl": "https://balkanmedicaljournal.org/text.php?lang=en&id=555",
    "sourcePdfUrl": "https://balkanmedicaljournal.org/pdf.php?&id=555",
    "localPdfUrl": "js/data/pdfs/555.pdf",
    "pdfUrl": "js/data/pdfs/555.pdf"
  },
  {
    "id": 557,
    "type": "Original Article",
    "title": "1983-1987 Senelerinde Trakya Üniversitesi Tıp Fakültesi",
    "authors": [
      {
        "name": "T. Yardım",
        "affiliation": "Trakya Üniversitesi Tıp Fakültesi Kadın Hastalıkları ve Doğum Anabilim Dalı Öğretim Üyesi (Doç. Dr.) Edirne",
        "orcid": ""
      },
      {
        "name": "G. Y. Dellaloğlu",
        "affiliation": "Trakya Üniversitesi Tıp Fakültesi Kadın Hastalıkları ve Doğum Anabilim Dalı Öğretim Üyesi (Yard. Doç. Dr.) Edirne",
        "orcid": ""
      },
      {
        "name": "G. Çinko",
        "affiliation": "Trakya Üniversitesi Tıp Fakültesi Kadın Hastalıkları ve Doğum Anabilim Dalı Araştırma Görevlisi Edirne",
        "orcid": ""
      }
    ],
    "abstract": "",
    "abstractHtml": "",
    "previewText": "",
    "keywords": [],
    "doi": "",
    "received": "",
    "accepted": "",
    "published": "1986-01-01",
    "volume": 3,
    "issue": "3",
    "pages": "153-157",
    "views": 5312,
    "downloads": 1545,
    "citations": 0,
    "featured": false,
    "imageCorner": false,
    "hasFullText": false,
    "sourceIssueId": "1105",
    "sourceArticleId": "557",
    "sourceAbstractUrl": "https://balkanmedicaljournal.org/abstract.php?id=557",
    "sourceTextUrl": "https://balkanmedicaljournal.org/text.php?lang=en&id=557",
    "sourcePdfUrl": "https://balkanmedicaljournal.org/pdf.php?&id=557",
    "localPdfUrl": "js/data/pdfs/557.pdf",
    "pdfUrl": "js/data/pdfs/557.pdf"
  },
  {
    "id": 558,
    "type": "Original Article",
    "title": "Bir Tbc Tiroidit Vakası *",
    "authors": [
      {
        "name": "S. Okay",
        "affiliation": "Trakya Üniversitesi Tıp Fakültesi Nükleer Tıp Ana Bilim Dalı Edirne",
        "orcid": ""
      },
      {
        "name": "Ş. Berkarda",
        "affiliation": "Trakya Üniversitesi Tıp Fakültesi İç Hastalıkları Anabilim Dalı - Edirne",
        "orcid": ""
      },
      {
        "name": "G. Özbay",
        "affiliation": "Trakya Üniversitesi Tıp Fakültesi İç Hastalıkları Anabilim Dalı - Edirne",
        "orcid": ""
      },
      {
        "name": "A. Tuğrul",
        "affiliation": "Trakya Üniversitesi Tıp Fakültesi İç Hastalıkları Anabilim Dalı - Edirne",
        "orcid": ""
      },
      {
        "name": "M. Tuğrul",
        "affiliation": "Trakya Üniversitesi Tıp Fakültesi Ana Bilim Dalı Edirne",
        "orcid": ""
      }
    ],
    "abstract": "",
    "abstractHtml": "",
    "previewText": "",
    "keywords": [],
    "doi": "",
    "received": "",
    "accepted": "",
    "published": "1986-01-01",
    "volume": 3,
    "issue": "3",
    "pages": "161-163",
    "views": 5640,
    "downloads": 1590,
    "citations": 0,
    "featured": false,
    "imageCorner": false,
    "hasFullText": false,
    "sourceIssueId": "1105",
    "sourceArticleId": "558",
    "sourceAbstractUrl": "https://balkanmedicaljournal.org/abstract.php?id=558",
    "sourceTextUrl": "https://balkanmedicaljournal.org/text.php?lang=en&id=558",
    "sourcePdfUrl": "https://balkanmedicaljournal.org/pdf.php?&id=558",
    "localPdfUrl": "js/data/pdfs/558.pdf",
    "pdfUrl": "js/data/pdfs/558.pdf"
  },
  {
    "id": 559,
    "type": "Original Article",
    "title": "Bir İntraabdominal Ria Olgusu Nedeniyle RİA Komplikasyonları",
    "authors": [
      {
        "name": "T. Yardım",
        "affiliation": "Trakya Üniversitesi Tıp Fakültesi Kadın Hastalıkları ve Doğum Anabilim Dalı Öğretim Üyesi (Doç. Dr.) Edirne",
        "orcid": ""
      },
      {
        "name": "L. Kıvrıkoğlu",
        "affiliation": "Trakya Üniversitesi Tıp Fakültesi Kadın Hastalıkları ve Doğum Anabilim Dalı (Araştırma Gör.) Edirne",
        "orcid": ""
      },
      {
        "name": "Ş. Karahasan",
        "affiliation": "Trakya Üniversitesi Tıp Fak. Kadın Hast. Anabilim Dalı (Araşt. Gör.) Edirne",
        "orcid": ""
      }
    ],
    "abstract": "",
    "abstractHtml": "",
    "previewText": "",
    "keywords": [],
    "doi": "",
    "received": "",
    "accepted": "",
    "published": "1986-01-01",
    "volume": 3,
    "issue": "3",
    "pages": "164-170",
    "views": 5613,
    "downloads": 1642,
    "citations": 0,
    "featured": false,
    "imageCorner": false,
    "hasFullText": false,
    "sourceIssueId": "1105",
    "sourceArticleId": "559",
    "sourceAbstractUrl": "https://balkanmedicaljournal.org/abstract.php?id=559",
    "sourceTextUrl": "https://balkanmedicaljournal.org/text.php?lang=en&id=559",
    "sourcePdfUrl": "https://balkanmedicaljournal.org/pdf.php?&id=559",
    "localPdfUrl": "js/data/pdfs/559.pdf",
    "pdfUrl": "js/data/pdfs/559.pdf"
  },
  {
    "id": 560,
    "type": "Original Article",
    "title": "Edirne",
    "authors": [
      {
        "name": "A. Görgülü",
        "affiliation": "Trakya Üniversitesi Tıp Fakültesi Dermatoloji Anabilim Dalı Öğretim Üyesi (Yard. Doç. Dr.) Edirne",
        "orcid": ""
      }
    ],
    "abstract": "",
    "abstractHtml": "",
    "previewText": "",
    "keywords": [],
    "doi": "",
    "received": "",
    "accepted": "",
    "published": "1986-01-01",
    "volume": 3,
    "issue": "3",
    "pages": "174-177",
    "views": 5568,
    "downloads": 1595,
    "citations": 0,
    "featured": false,
    "imageCorner": false,
    "hasFullText": false,
    "sourceIssueId": "1105",
    "sourceArticleId": "560",
    "sourceAbstractUrl": "https://balkanmedicaljournal.org/abstract.php?id=560",
    "sourceTextUrl": "https://balkanmedicaljournal.org/text.php?lang=en&id=560",
    "sourcePdfUrl": "https://balkanmedicaljournal.org/pdf.php?&id=560",
    "localPdfUrl": "js/data/pdfs/560.pdf",
    "pdfUrl": "js/data/pdfs/560.pdf"
  },
  {
    "id": 561,
    "type": "Original Article",
    "title": "Hirsutismus Üzerine Bir Klinik Çalışma",
    "authors": [
      {
        "name": "T. Yardım",
        "affiliation": "Trakya Üniversitesi Tıp Fakültesi Kadın Hastalıkları ve Doğum Anabilim Dalı Öğretim Üyesi (Doç. Dr.) Edirne",
        "orcid": ""
      },
      {
        "name": "L. Kıvrıkoğlu",
        "affiliation": "Trakya Üniversitesi Tıp Fakültesi Kadın Hastalıkları ve Doğum Anabilim Dalı (Araştırma Gör.) Edirne",
        "orcid": ""
      },
      {
        "name": "A. Yüce",
        "affiliation": "Trakya Üniversitesi Tıp Fakültesi Kadın Hastalıkları ve Doğum Anabilim Dalı Araştırma Görevlisi EDİRNE",
        "orcid": ""
      }
    ],
    "abstract": "",
    "abstractHtml": "",
    "previewText": "",
    "keywords": [],
    "doi": "",
    "received": "",
    "accepted": "",
    "published": "1986-01-01",
    "volume": 3,
    "issue": "3",
    "pages": "178-183",
    "views": 5376,
    "downloads": 1735,
    "citations": 0,
    "featured": false,
    "imageCorner": false,
    "hasFullText": false,
    "sourceIssueId": "1105",
    "sourceArticleId": "561",
    "sourceAbstractUrl": "https://balkanmedicaljournal.org/abstract.php?id=561",
    "sourceTextUrl": "https://balkanmedicaljournal.org/text.php?lang=en&id=561",
    "sourcePdfUrl": "https://balkanmedicaljournal.org/pdf.php?&id=561",
    "localPdfUrl": "js/data/pdfs/561.pdf",
    "pdfUrl": "js/data/pdfs/561.pdf"
  },
  {
    "id": 562,
    "type": "Original Article",
    "title": "Preoperative İCB Monitoring (x).",
    "authors": [
      {
        "name": "S. Çobanoğlu",
        "affiliation": "Trakya Üniversitesi Tıp Fakültesi Nöroşirorji Anabilim Dalı Öğretim Üyesi (Yard. Doç. Dr.) Edirne",
        "orcid": ""
      }
    ],
    "abstract": "",
    "abstractHtml": "",
    "previewText": "",
    "keywords": [],
    "doi": "",
    "received": "",
    "accepted": "",
    "published": "1986-01-01",
    "volume": 3,
    "issue": "3",
    "pages": "187-199",
    "views": 5510,
    "downloads": 1610,
    "citations": 0,
    "featured": false,
    "imageCorner": false,
    "hasFullText": false,
    "sourceIssueId": "1105",
    "sourceArticleId": "562",
    "sourceAbstractUrl": "https://balkanmedicaljournal.org/abstract.php?id=562",
    "sourceTextUrl": "https://balkanmedicaljournal.org/text.php?lang=en&id=562",
    "sourcePdfUrl": "https://balkanmedicaljournal.org/pdf.php?&id=562",
    "localPdfUrl": "js/data/pdfs/562.pdf",
    "pdfUrl": "js/data/pdfs/562.pdf"
  },
  {
    "id": 563,
    "type": "Original Article",
    "title": "Maternal Epilepsi, Antikonvülsan Tedavisi ve Perinatal Riskleri",
    "authors": [
      {
        "name": "T. Yardım",
        "affiliation": "Trakya Üniversitesi Tıp Fakültesi Kadın Hastalıkları ve Doğum Anabilim Dalı Öğretim Üyesi (Doç. Dr.) Edirne",
        "orcid": ""
      },
      {
        "name": "Ş. Karahasan",
        "affiliation": "Trakya Üniversitesi Tıp Fak. Kadın Hast. Anabilim Dalı (Araşt. Gör.) Edirne",
        "orcid": ""
      },
      {
        "name": "L. Kıvrıkoğlu",
        "affiliation": "Trakya Üniversitesi Tıp Fakültesi Kadın Hastalıkları ve Doğum Anabilim Dalı (Araştırma Gör.) Edirne",
        "orcid": ""
      }
    ],
    "abstract": "",
    "abstractHtml": "",
    "previewText": "",
    "keywords": [],
    "doi": "",
    "received": "",
    "accepted": "",
    "published": "1986-01-01",
    "volume": 3,
    "issue": "3",
    "pages": "200-210",
    "views": 5383,
    "downloads": 1635,
    "citations": 0,
    "featured": false,
    "imageCorner": false,
    "hasFullText": false,
    "sourceIssueId": "1105",
    "sourceArticleId": "563",
    "sourceAbstractUrl": "https://balkanmedicaljournal.org/abstract.php?id=563",
    "sourceTextUrl": "https://balkanmedicaljournal.org/text.php?lang=en&id=563",
    "sourcePdfUrl": "https://balkanmedicaljournal.org/pdf.php?&id=563",
    "localPdfUrl": "js/data/pdfs/563.pdf",
    "pdfUrl": "js/data/pdfs/563.pdf"
  },
  {
    "id": 564,
    "type": "Original Article",
    "title": "Herediter Lens Ektopileri",
    "authors": [
      {
        "name": "N. Şenol",
        "affiliation": "Trakya Üniv. Rektörlüğü Göz Hastalıkları Uzmanı. Edirne",
        "orcid": ""
      },
      {
        "name": "S. Erda",
        "affiliation": "Trakya Üniversitesi Tıp Fakültesi Göz Hastaıkları Ana Bilim Dalı Öğretim Üyesi (Doç Dr.) Edirne",
        "orcid": ""
      }
    ],
    "abstract": "",
    "abstractHtml": "",
    "previewText": "",
    "keywords": [],
    "doi": "",
    "received": "",
    "accepted": "",
    "published": "1986-01-01",
    "volume": 3,
    "issue": "3",
    "pages": "211-219",
    "views": 5472,
    "downloads": 1544,
    "citations": 0,
    "featured": false,
    "imageCorner": false,
    "hasFullText": false,
    "sourceIssueId": "1105",
    "sourceArticleId": "564",
    "sourceAbstractUrl": "https://balkanmedicaljournal.org/abstract.php?id=564",
    "sourceTextUrl": "https://balkanmedicaljournal.org/text.php?lang=en&id=564",
    "sourcePdfUrl": "https://balkanmedicaljournal.org/pdf.php?&id=564",
    "localPdfUrl": "js/data/pdfs/564.pdf",
    "pdfUrl": "js/data/pdfs/564.pdf"
  },
  {
    "id": 565,
    "type": "Original Article",
    "title": "Femur Üst Uç Kanlanması",
    "authors": [
      {
        "name": "O. U. Çalpur",
        "affiliation": "Trakya Üniversitesi Tıp Fakültesi Ortopedi ve Travmatoloji Anabilim Dalı Öğretim Üyesi (Yard. Doç. Dr.) Edirne",
        "orcid": ""
      }
    ],
    "abstract": "",
    "abstractHtml": "",
    "previewText": "",
    "keywords": [],
    "doi": "",
    "received": "",
    "accepted": "",
    "published": "1986-01-01",
    "volume": 3,
    "issue": "3",
    "pages": "220-223",
    "views": 5213,
    "downloads": 1665,
    "citations": 0,
    "featured": false,
    "imageCorner": false,
    "hasFullText": false,
    "sourceIssueId": "1105",
    "sourceArticleId": "565",
    "sourceAbstractUrl": "https://balkanmedicaljournal.org/abstract.php?id=565",
    "sourceTextUrl": "https://balkanmedicaljournal.org/text.php?lang=en&id=565",
    "sourcePdfUrl": "https://balkanmedicaljournal.org/pdf.php?&id=565",
    "localPdfUrl": "js/data/pdfs/565.pdf",
    "pdfUrl": "js/data/pdfs/565.pdf"
  },
  {
    "id": 566,
    "type": "Original Article",
    "title": "Growing Skull Fractures Of Childhood",
    "authors": [
      {
        "name": "S. Çobanoğlu",
        "affiliation": "Trakya Üniversitesi Tıp Fakültesi Nöroşirorji Anabilim Dalı Öğretim Üyesi (Yard. Doç. Dr.) Edirne",
        "orcid": ""
      },
      {
        "name": "Z. A. Medeni",
        "affiliation": "Trakya Tıp Fakültesi Çocuk Sağlığı ve Hastalıkları Anabilim Dalı Öğretim Üyesi (Yard. Doç. Dr.) Edirne",
        "orcid": ""
      }
    ],
    "abstract": "",
    "abstractHtml": "",
    "previewText": "",
    "keywords": [],
    "doi": "",
    "received": "",
    "accepted": "",
    "published": "1986-01-01",
    "volume": 3,
    "issue": "3",
    "pages": "224-227",
    "views": 5294,
    "downloads": 1589,
    "citations": 0,
    "featured": false,
    "imageCorner": false,
    "hasFullText": false,
    "sourceIssueId": "1105",
    "sourceArticleId": "566",
    "sourceAbstractUrl": "https://balkanmedicaljournal.org/abstract.php?id=566",
    "sourceTextUrl": "https://balkanmedicaljournal.org/text.php?lang=en&id=566",
    "sourcePdfUrl": "https://balkanmedicaljournal.org/pdf.php?&id=566",
    "localPdfUrl": "js/data/pdfs/566.pdf",
    "pdfUrl": "js/data/pdfs/566.pdf"
  },
  {
    "id": 567,
    "type": "Original Article",
    "title": "Gebelik ve Jinekolojide Aıds",
    "authors": [
      {
        "name": "L. Kıvrıkoğlu",
        "affiliation": "Trakya Üniversitesi Tıp Fakültesi Kadın Hastalıkları ve Doğum Anabilim Dalı (Araştırma Gör.) Edirne",
        "orcid": ""
      },
      {
        "name": "T. Yardım",
        "affiliation": "Trakya Üniversitesi Tıp Fakültesi Kadın Hastalıkları ve Doğum Anabilim Dalı Öğretim Üyesi (Doç. Dr.) Edirne",
        "orcid": ""
      },
      {
        "name": "S. Kıvrıkoğlu",
        "affiliation": "Trakya Tıp Fak. Dermtoloji Anabilim Dalı EDİRNE",
        "orcid": ""
      }
    ],
    "abstract": "",
    "abstractHtml": "",
    "previewText": "",
    "keywords": [],
    "doi": "",
    "received": "",
    "accepted": "",
    "published": "1986-01-01",
    "volume": 3,
    "issue": "3",
    "pages": "228-231",
    "views": 5266,
    "downloads": 1627,
    "citations": 0,
    "featured": false,
    "imageCorner": false,
    "hasFullText": false,
    "sourceIssueId": "1105",
    "sourceArticleId": "567",
    "sourceAbstractUrl": "https://balkanmedicaljournal.org/abstract.php?id=567",
    "sourceTextUrl": "https://balkanmedicaljournal.org/text.php?lang=en&id=567",
    "sourcePdfUrl": "https://balkanmedicaljournal.org/pdf.php?&id=567",
    "localPdfUrl": "js/data/pdfs/567.pdf",
    "pdfUrl": "js/data/pdfs/567.pdf"
  }
]